{
  "schema_version": "1",
  "open_source": true,
  "model_name": "poker44-core-detector",
  "model_version": "1",
  "framework": "mlp",
  "license": "MIT",
  "repo_url": "https://github.com/danielstardev/yuki-demon-1",
  "repo_commit": "",
  "artifact_sha256": "81ee28ca788eb5ec3a9f034a2d689c795866f9a415cd8226c21a112b33b9b738",
  "artifact_basename": "current.joblib",
  "implementation_sha256": "73f3d28c641279b53490ca318e961ff78ec2f7e075fbb0480d3bcf5dc20b896d",
  "implementation_files": [
    "neurons/miner.py",
    "poker44_ml/inference.py",
    "poker44_ml/features.py",
    "poker44_ml/sequence_model.py",
    "poker44_ml/stacked.py",
    "poker44_ml/calibration.py",
    "poker44_ml/batch_calibration.py",
    "poker44/validator/payload_view.py"
  ],
  "inference_mode": "local-joblib",
  "training_data_statement": "Trained on the Poker44 public training benchmark (api.poker44.net). No validator-private evaluation data used.",
  "training_data_sources": [
    "released_training_benchmark"
  ],
  "private_data_attestation": "No validator-private data used. Supervised artifacts use released benchmark labels only.",
  "data_attestation": "No validator-private data used. Supervised artifacts use released benchmark labels only."
}
